Metadata-Version: 2.4
Name: evehap
Version: 0.1.1
Summary: Universal mtDNA Haplogroup Classifier
Author: eveHap Authors
License: PolyForm Noncommercial License 1.0.0
Project-URL: Homepage, https://github.com/trianglegrrl/eveHap
Project-URL: Documentation, https://github.com/trianglegrrl/eveHap#readme
Project-URL: Repository, https://github.com/trianglegrrl/eveHap
Keywords: mtdna,haplogroup,genetics,phylogenetics,ancient-dna
Classifier: Development Status :: 4 - Beta
Classifier: Intended Audience :: Science/Research
Classifier: License :: Other/Proprietary License
Classifier: Programming Language :: Python :: 3
Classifier: Programming Language :: Python :: 3.8
Classifier: Programming Language :: Python :: 3.9
Classifier: Programming Language :: Python :: 3.10
Classifier: Programming Language :: Python :: 3.11
Classifier: Programming Language :: Python :: 3.12
Classifier: Topic :: Scientific/Engineering :: Bio-Informatics
Requires-Python: >=3.8
License-File: LICENSE
Requires-Dist: click>=8.0
Requires-Dist: pysam>=0.21.0
Requires-Dist: biopython>=1.80
Provides-Extra: dev
Requires-Dist: pytest>=7.0; extra == "dev"
Requires-Dist: pytest-cov>=4.0; extra == "dev"
Requires-Dist: ruff>=0.1.0; extra == "dev"
Requires-Dist: mypy>=1.0; extra == "dev"
Requires-Dist: black>=23.0; extra == "dev"
Provides-Extra: validation
Requires-Dist: tqdm>=4.65; extra == "validation"
Requires-Dist: pandas>=2.0; extra == "validation"
Requires-Dist: tabulate>=0.9; extra == "validation"
Dynamic: license-file
